coinor.blimpy-2.0.0-py3.7-nspkg.pth
coinor/blimpy/LinkedList.py
coinor/blimpy/Queues.py
coinor/blimpy/Stack.py
coinor/blimpy/__init__.py
coinor.blimpy-2.0.0.dist-info/AUTHORS
coinor.blimpy-2.0.0.dist-info/LICENSE
coinor.blimpy-2.0.0.dist-info/METADATA
coinor.blimpy-2.0.0.dist-info/WHEEL
coinor.blimpy-2.0.0.dist-info/namespace_packages.txt
coinor.blimpy-2.0.0.dist-info/top_level.txt
coinor.blimpy-2.0.0.dist-info/RECORD
