Metadata-Version: 2.1
Name: coinor.blimpy
Version: 2.0.0
Summary: Basic List Implementation in Python
Home-page: http://projects.coin-or.org/CoinBazaar/wiki/Projects/GIMPy
Author: Aykut Bulut, Ted Ralphs
Author-email: ted@lehigh.edu
License: Eclipse Public License
Platform: UNKNOWN
